{"_default": {"1": {"STOCK": "SAGAR CEMENTS LTD", "SOURCE": "BREEZE-iCLICK", "STRATEGY": "GLADIATOR STOCKS", "BUY_SELL": "BUY", "REC_DATE": "05-Jun-2024", "EXP_DATE": "05-Sep-2024", "VISIBLE": "VISIBLE", "REC_STATUS": "PARTIAL_CLOSE", "UPDATE_ACTION_1": "  Book Partial Profit:2024-06-06 09:31:13   ", "UPDATE_TIME_1": "09:31:13", "UPDATE_ACTION_2": "", "UPDATE_TIME_2": "", "PRODUCT": "CASH", "MKT_SYMBOL": "SAGCEM", "ICICI_SYMBOL": "SAGCEM", "SECURITY_ID": "4.1!14068", "MKT": "NSE", "LOW_REC_PRICE": 197.0, "HIGH_REC_PRICE": 207.0, "TARGET": 236.0, "STOP_LOSS": 212.0, "REC_TIME": "14:46", "PART_PROFIT_PRICE": "224.3", "FINAL_PROFIT_PRICE": "0", "EXIT_PRICE": "0", "ACK": "ACK"}, "2": {"STOCK": "VA TECH WABAG LIMITED", "SOURCE": "BREEZE-iCLICK", "STRATEGY": "GLADIATOR STOCKS", "BUY_SELL": "BUY", "REC_DATE": "06-Jun-2024", "EXP_DATE": "06-Sep-2024", "VISIBLE": "VISIBLE", "REC_STATUS": "PARTIAL_CLOSE", "UPDATE_ACTION_1": "  Book Partial Profit:2024-06-06 13:29:53   ", "UPDATE_TIME_1": "13:29:53", "UPDATE_ACTION_2": "", "UPDATE_TIME_2": "", "PRODUCT": "CASH", "MKT_SYMBOL": "WABAG", "ICICI_SYMBOL": "VATWAB", "SECURITY_ID": "4.1!20188", "MKT": "NSE", "LOW_REC_PRICE": 980.0, "HIGH_REC_PRICE": 1008.0, "TARGET": 1145.0, "STOP_LOSS": 1010.0, "REC_TIME": "09:44", "PART_PROFIT_PRICE": "1080", "FINAL_PROFIT_PRICE": "0", "EXIT_PRICE": "0", "ACK": "ACK"}, "3": {"STOCK": "THE RAMCO CEMENTS LIMITED", "SOURCE": "BREEZE-iCLICK", "STRATEGY": "MOMENTUM PICK", "BUY_SELL": "BUY", "REC_DATE": "06-Jun-2024", "EXP_DATE": "20-Jun-2024", "VISIBLE": "VISIBLE", "REC_STATUS": "CLOSE", "UPDATE_ACTION_1": "Book Partial Profit:2024-06-07 09:40:34   ", "UPDATE_TIME_1": "09:40:34", "UPDATE_ACTION_2": " Book Full Profit:2024-06-07 11:45:40", "UPDATE_TIME_2": "11:45:40", "PRODUCT": "CASH", "MKT_SYMBOL": "RAMCOCEM", "ICICI_SYMBOL": "RAMCEM", "SECURITY_ID": "4.1!2043", "MKT": "NSE", "LOW_REC_PRICE": 760.0, "HIGH_REC_PRICE": 780.0, "TARGET": 832.0, "STOP_LOSS": 780.0, "REC_TIME": "10:34", "PART_PROFIT_PRICE": "809", "FINAL_PROFIT_PRICE": "829", "EXIT_PRICE": "0", "ACK": "ACK", "LOT": 1}, "4": {"STOCK": "BATA INDIA LIMITED", "SOURCE": "BREEZE-iCLICK", "STRATEGY": "QUANT PICKS", "BUY_SELL": "BUY", "REC_DATE": "06-Jun-2024", "EXP_DATE": "06-Sep-2024", "VISIBLE": "VISIBLE", "REC_STATUS": "OPEN", "UPDATE_ACTION_1": "", "UPDATE_TIME_1": "", "UPDATE_ACTION_2": "", "UPDATE_TIME_2": "", "PRODUCT": "CASH", "MKT_SYMBOL": "BATAINDIA", "ICICI_SYMBOL": "BATIND", "SECURITY_ID": "4.1!371", "MKT": "NSE", "LOW_REC_PRICE": 1410.0, "HIGH_REC_PRICE": 1430.0, "TARGET": 1625.0, "STOP_LOSS": 1300.0, "REC_TIME": "10:38", "PART_PROFIT_PRICE": "0", "FINAL_PROFIT_PRICE": "0", "EXIT_PRICE": "0", "ACK": "ACK"}, "5": {"STOCK": "NATCO PHARMA LIMITED", "SOURCE": "BREEZE-iCLICK", "STRATEGY": "GLADIATOR STOCKS", "BUY_SELL": "BUY", "REC_DATE": "05-Jun-2024", "REC_TIME": "10:10", "EXP_DATE": "05-Sep-2024", "SECURITY_ID": "4.1!3918", "ICICI_SYMBOL": "NATPHA", "MKT_SYMBOL": "NATCOPHARM", "MKT": "NSE", "LOT": 1, "PRODUCT": "CASH", "REC_STATUS": "CLOSE", "UPDATE_ACTION_1": "Book Partial Profit:2024-06-07 09:44:34 TGT1:2024-06-11 12:47:45  ", "UPDATE_TIME_1": "09:44:34", "UPDATE_ACTION_2": "  Book Partial Profit:2024-06-07 09:44:34", "UPDATE_TIME_2": "09:44:34", "LOW_REC_PRICE": 1000.0, "HIGH_REC_PRICE": 1020.0, "TARGET": 1150.0, "STOP_LOSS": 1016.0, "PART_PROFIT_PRICE": "1093", "FINAL_PROFIT_PRICE": "0", "EXIT_PRICE": "0", "ACK": "ACK"}, "6": {"STOCK": "LARSEN AND TOUBRO LIMITED", "SOURCE": "BREEZE-iCLICK", "STRATEGY": "GLADIATOR STOCKS", "BUY_SELL": "BUY", "REC_DATE": "07-Jun-2024", "REC_TIME": "10:46", "EXP_DATE": "07-Sep-2024", "SECURITY_ID": "4.1!11483", "ICICI_SYMBOL": "LARTOU", "MKT_SYMBOL": "LT", "MKT": "NSE", "LOT": 1, "PRODUCT": "CASH", "REC_STATUS": "OPEN", "UPDATE_ACTION_1": "", "UPDATE_TIME_1": "", "UPDATE_ACTION_2": "", "UPDATE_TIME_2": "", "LOW_REC_PRICE": 3420.0, "HIGH_REC_PRICE": 3500.0, "TARGET": 3870.0, "STOP_LOSS": 3280.0, "PART_PROFIT_PRICE": "0", "FINAL_PROFIT_PRICE": "0", "EXIT_PRICE": "0", "ACK": "ACK"}, "7": {"STOCK": "AXIS BANK LIMITED", "SOURCE": "BREEZE-iCLICK", "STRATEGY": "MOMENTUM PICK", "BUY_SELL": "BUY", "REC_DATE": "07-Jun-2024", "REC_TIME": "11:42", "EXP_DATE": "21-Jun-2024", "SECURITY_ID": "4.1!5900", "ICICI_SYMBOL": "AXIBAN", "MKT_SYMBOL": "AXISBANK", "MKT": "NSE", "LOT": 1, "PRODUCT": "CASH", "REC_STATUS": "OPEN", "UPDATE_ACTION_1": "", "UPDATE_TIME_1": "", "UPDATE_ACTION_2": "", "UPDATE_TIME_2": "", "LOW_REC_PRICE": 1165.0, "HIGH_REC_PRICE": 1185.0, "TARGET": 1270.0, "STOP_LOSS": 1118.0, "PART_PROFIT_PRICE": "0", "FINAL_PROFIT_PRICE": "0", "EXIT_PRICE": "0", "ACK": "ACK"}, "8": {"STOCK": "POWER FINANCE CORPORATION LTD", "SOURCE": "BREEZE-iCLICK", "STRATEGY": "MOMENTUM PICK", "BUY_SELL": "BUY", "REC_DATE": "07-Jun-2024", "REC_TIME": "14:10", "EXP_DATE": "21-Jun-2024", "SECURITY_ID": "4.1!14299", "ICICI_SYMBOL": "POWFIN", "MKT_SYMBOL": "PFC", "MKT": "NSE", "LOT": 1, "PRODUCT": "CASH", "REC_STATUS": "PARTIAL_CLOSE", "UPDATE_ACTION_1": "  Book Partial Profit:2024-06-12 13:05:34   ", "UPDATE_TIME_1": "13:05:34", "UPDATE_ACTION_2": "", "UPDATE_TIME_2": "", "LOW_REC_PRICE": 470.0, "HIGH_REC_PRICE": 480.0, "TARGET": 514.0, "STOP_LOSS": 479.0, "PART_PROFIT_PRICE": "497.5", "FINAL_PROFIT_PRICE": "0", "EXIT_PRICE": "0", "ACK": "ACK"}, "9": {"STOCK": "CHAMBAL FERTILISERS & CHEMICAL", "SOURCE": "BREEZE-iCLICK", "STRATEGY": "MOMENTUM PICK", "BUY_SELL": "BUY", "REC_DATE": "10-Jun-2024", "REC_TIME": "10:22", "EXP_DATE": "24-Jun-2024", "SECURITY_ID": "4.1!637", "ICICI_SYMBOL": "CHAFER", "MKT_SYMBOL": "CHAMBLFERT", "MKT": "NSE", "LOT": 1, "PRODUCT": "CASH", "REC_STATUS": "PARTIAL_CLOSE", "UPDATE_ACTION_1": "  Book Partial Profit:2024-06-11 09:21:00   ", "UPDATE_TIME_1": "09:21:00", "UPDATE_ACTION_2": "", "UPDATE_TIME_2": "", "LOW_REC_PRICE": 405.0, "HIGH_REC_PRICE": 415.0, "TARGET": 446.0, "STOP_LOSS": 415.0, "PART_PROFIT_PRICE": "429", "FINAL_PROFIT_PRICE": "0", "EXIT_PRICE": "0", "ACK": "ACK"}, "10": {"STOCK": "PNB HOUSING FINANCE LIMITED", "SOURCE": "BREEZE-iCLICK", "STRATEGY": "GLADIATOR STOCKS", "BUY_SELL": "BUY", "REC_DATE": "11-Jun-2024", "REC_TIME": "10:19", "EXP_DATE": "11-Sep-2024", "SECURITY_ID": "4.1!18908", "ICICI_SYMBOL": "PNBHOU", "MKT_SYMBOL": "PNBHOUSING", "MKT": "NSE", "LOT": 1, "PRODUCT": "CASH", "REC_STATUS": "OPEN", "UPDATE_ACTION_1": "", "UPDATE_TIME_1": "", "UPDATE_ACTION_2": "", "UPDATE_TIME_2": "", "LOW_REC_PRICE": 765.0, "HIGH_REC_PRICE": 785.0, "TARGET": 896.0, "STOP_LOSS": 714.0, "PART_PROFIT_PRICE": "0", "FINAL_PROFIT_PRICE": "0", "EXIT_PRICE": "0", "ACK": "ACK"}, "11": {"STOCK": "GIC HOUSING FINANCE LTD", "SOURCE": "BREEZE-iCLICK", "STRATEGY": "MOMENTUM PICK", "BUY_SELL": "BUY", "REC_DATE": "11-Jun-2024", "REC_TIME": "10:44", "EXP_DATE": "25-Jun-2024", "SECURITY_ID": "4.1!1139", "ICICI_SYMBOL": "GICHOU", "MKT_SYMBOL": "GICHSGFIN", "MKT": "NSE", "LOT": 1, "PRODUCT": "CASH", "REC_STATUS": "PARTIAL_CLOSE", "UPDATE_ACTION_1": "  Book Partial Profit:2024-06-12 10:15:30   ", "UPDATE_TIME_1": "10:15:30", "UPDATE_ACTION_2": "", "UPDATE_TIME_2": "", "LOW_REC_PRICE": 226.0, "HIGH_REC_PRICE": 231.0, "TARGET": 250.0, "STOP_LOSS": 234.0, "PART_PROFIT_PRICE": "243.75", "FINAL_PROFIT_PRICE": "0", "EXIT_PRICE": "0", "ACK": "ACK"}, "12": {"STOCK": "PVR INOX LIMITED", "SOURCE": "BREEZE-iCLICK", "STRATEGY": "QUANT PICKS", "BUY_SELL": "BUY", "REC_DATE": "11-Jun-2024", "REC_TIME": "11:56", "EXP_DATE": "11-Sep-2024", "SECURITY_ID": "4.1!13147", "ICICI_SYMBOL": "PVRLIM", "MKT_SYMBOL": "PVRINOX", "MKT": "NSE", "LOT": 1, "PRODUCT": "CASH", "REC_STATUS": "OPEN", "UPDATE_ACTION_1": "", "UPDATE_TIME_1": "", "UPDATE_ACTION_2": "", "UPDATE_TIME_2": "", "LOW_REC_PRICE": 1360.0, "HIGH_REC_PRICE": 1375.0, "TARGET": 1550.0, "STOP_LOSS": 1270.0, "PART_PROFIT_PRICE": "0", "FINAL_PROFIT_PRICE": "0", "EXIT_PRICE": "0", "ACK": "ACK"}, "13": {"STOCK": "TATA MOTORS LIMITED", "SOURCE": "BREEZE-iCLICK", "STRATEGY": "MARGIN", "BUY_SELL": "BUY", "REC_DATE": "12-Jun-2024", "REC_TIME": "08:46", "EXP_DATE": "12-Jun-2024", "SECURITY_ID": "4.1!3456", "ICICI_SYMBOL": "TATMOT", "MKT_SYMBOL": "TATAMOTORS", "MKT": "NSE", "LOT": 1, "PRODUCT": "CASH", "REC_STATUS": "CLOSE", "UPDATE_ACTION_1": "   TGT1:2024-06-12 09:30:02  ", "UPDATE_TIME_1": "09:30:02", "UPDATE_ACTION_2": "", "UPDATE_TIME_2": "", "LOW_REC_PRICE": 987.0, "HIGH_REC_PRICE": 989.0, "TARGET": 998.0, "STOP_LOSS": 937.0, "PART_PROFIT_PRICE": "0", "FINAL_PROFIT_PRICE": "0", "EXIT_PRICE": "0", "ACK": "ACK"}, "14": {"STOCK": "DHAMPUR SUGAR MILLS LTD", "SOURCE": "BREEZE-iCLICK", "STRATEGY": "MARGIN", "BUY_SELL": "BUY", "REC_DATE": "12-Jun-2024", "REC_TIME": "09:46", "EXP_DATE": "12-Jun-2024", "SECURITY_ID": "4.1!857", "ICICI_SYMBOL": "DHASUG", "MKT_SYMBOL": "DHAMPURSUG", "MKT": "NSE", "LOT": 1, "PRODUCT": "CASH", "REC_STATUS": "CLOSE", "UPDATE_ACTION_1": " Book Full Profit:2024-06-12 09:53:09    ", "UPDATE_TIME_1": "09:53:09", "UPDATE_ACTION_2": "", "UPDATE_TIME_2": "", "LOW_REC_PRICE": 238.0, "HIGH_REC_PRICE": 239.0, "TARGET": 242.0, "STOP_LOSS": 226.0, "PART_PROFIT_PRICE": "0", "FINAL_PROFIT_PRICE": "241", "EXIT_PRICE": "0", "ACK": "ACK"}, "15": {"STOCK": "NATIONAL FERTILIZERS LIMITED", "SOURCE": "BREEZE-iCLICK", "STRATEGY": "MARGIN", "BUY_SELL": "BUY", "REC_DATE": "12-Jun-2024", "REC_TIME": "09:42", "EXP_DATE": "12-Jun-2024", "SECURITY_ID": "4.1!13925", "ICICI_SYMBOL": "NATFER", "MKT_SYMBOL": "NFL", "MKT": "NSE", "LOT": 1, "PRODUCT": "CASH", "REC_STATUS": "CLOSE", "UPDATE_ACTION_1": " Book Full Profit:2024-06-12 09:48:23    ", "UPDATE_TIME_1": "09:48:23", "UPDATE_ACTION_2": "", "UPDATE_TIME_2": "", "LOW_REC_PRICE": 114.0, "HIGH_REC_PRICE": 114.0, "TARGET": 116.0, "STOP_LOSS": 108.0, "PART_PROFIT_PRICE": "0", "FINAL_PROFIT_PRICE": "116", "EXIT_PRICE": "0", "ACK": "ACK"}, "16": {"STOCK": "CANARA BANK", "SOURCE": "BREEZE-iCLICK", "STRATEGY": "MARGIN", "BUY_SELL": "BUY", "REC_DATE": "12-Jun-2024", "REC_TIME": "08:51", "EXP_DATE": "12-Jun-2024", "SECURITY_ID": "4.1!10794", "ICICI_SYMBOL": "CANBAN", "MKT_SYMBOL": "CANBK", "MKT": "NSE", "LOT": 1, "PRODUCT": "CASH", "REC_STATUS": "CLOSE", "UPDATE_ACTION_1": " Book Full Profit:2024-06-12 09:34:43    ", "UPDATE_TIME_1": "09:34:43", "UPDATE_ACTION_2": "", "UPDATE_TIME_2": "", "LOW_REC_PRICE": 121.0, "HIGH_REC_PRICE": 121.0, "TARGET": 123.0, "STOP_LOSS": 115.0, "PART_PROFIT_PRICE": "0", "FINAL_PROFIT_PRICE": "122", "EXIT_PRICE": "0", "ACK": "ACK"}, "17": {"STOCK": "PETRONET LNG LIMITED", "SOURCE": "BREEZE-iCLICK", "STRATEGY": "MARGIN", "BUY_SELL": "BUY", "REC_DATE": "12-Jun-2024", "REC_TIME": "09:17", "EXP_DATE": "12-Jun-2024", "SECURITY_ID": "4.1!11351", "ICICI_SYMBOL": "PETLNG", "MKT_SYMBOL": "PETRONET", "MKT": "NSE", "LOT": 1, "PRODUCT": "CASH", "REC_STATUS": "CLOSE", "UPDATE_ACTION_1": "   TGT1:2024-06-12 09:25:32  ", "UPDATE_TIME_1": "09:25:32", "UPDATE_ACTION_2": "", "UPDATE_TIME_2": "", "LOW_REC_PRICE": 321.0, "HIGH_REC_PRICE": 322.0, "TARGET": 325.0, "STOP_LOSS": 304.0, "PART_PROFIT_PRICE": "0", "FINAL_PROFIT_PRICE": "0", "EXIT_PRICE": "0", "ACK": "ACK"}, "18": {"STOCK": "TATA CHEMICALS LTD", "SOURCE": "BREEZE-iCLICK", "STRATEGY": "QUANT PICKS", "BUY_SELL": "BUY", "REC_DATE": "12-Jun-2024", "REC_TIME": "09:55", "EXP_DATE": "12-Sep-2024", "SECURITY_ID": "4.1!3405", "ICICI_SYMBOL": "TATCHE", "MKT_SYMBOL": "TATACHEM", "MKT": "NSE", "LOT": 1, "PRODUCT": "CASH", "REC_STATUS": "OPEN", "UPDATE_ACTION_1": "", "UPDATE_TIME_1": "", "UPDATE_ACTION_2": "", "UPDATE_TIME_2": "", "LOW_REC_PRICE": 1100.0, "HIGH_REC_PRICE": 1120.0, "TARGET": 1265.0, "STOP_LOSS": 1016.0, "PART_PROFIT_PRICE": "0", "FINAL_PROFIT_PRICE": "0", "EXIT_PRICE": "0", "ACK": "ACK"}, "19": {"STOCK": "CENTRAL BANK OF INDIA", "SOURCE": "BREEZE-iCLICK", "STRATEGY": "MARGIN", "BUY_SELL": "BUY", "REC_DATE": "12-Jun-2024", "REC_TIME": "10:06", "EXP_DATE": "12-Jun-2024", "SECURITY_ID": "4.1!14894", "ICICI_SYMBOL": "CENBAN", "MKT_SYMBOL": "CENTRALBK", "MKT": "NSE", "LOT": 1, "PRODUCT": "CASH", "REC_STATUS": "CLOSE", "UPDATE_ACTION_1": "   TGT1:2024-06-12 11:26:17  ", "UPDATE_TIME_1": "11:26:17", "UPDATE_ACTION_2": "", "UPDATE_TIME_2": "", "LOW_REC_PRICE": 65.0, "HIGH_REC_PRICE": 65.0, "TARGET": 66.0, "STOP_LOSS": 61.0, "PART_PROFIT_PRICE": "0", "FINAL_PROFIT_PRICE": "0", "EXIT_PRICE": "0", "ACK": "ACK"}, "20": {"STOCK": "INDIAN OIL CORPORATION LIMITED", "SOURCE": "BREEZE-iCLICK", "STRATEGY": "MARGIN", "BUY_SELL": "BUY", "REC_DATE": "12-Jun-2024", "REC_TIME": "09:24", "EXP_DATE": "12-Jun-2024", "SECURITY_ID": "4.1!1624", "ICICI_SYMBOL": "INDOIL", "MKT_SYMBOL": "IOC", "MKT": "NSE", "LOT": 1, "PRODUCT": "CASH", "REC_STATUS": "OPEN", "UPDATE_ACTION_1": "Exit:2024-06-12 10:07:19     ", "UPDATE_TIME_1": "10:07:19", "UPDATE_ACTION_2": "", "UPDATE_TIME_2": "", "LOW_REC_PRICE": 170.0, "HIGH_REC_PRICE": 171.0, "TARGET": 173.0, "STOP_LOSS": 161.0, "PART_PROFIT_PRICE": "0", "FINAL_PROFIT_PRICE": "0", "EXIT_PRICE": "170", "ACK": "ACK"}, "21": {"STOCK": "CENTRAL BANK OF INDIA", "SOURCE": "BREEZE-iCLICK", "STRATEGY": "MOMENTUM PICK", "BUY_SELL": "BUY", "REC_DATE": "12-Jun-2024", "REC_TIME": "10:26", "EXP_DATE": "26-Jun-2024", "SECURITY_ID": "4.1!14894", "ICICI_SYMBOL": "CENBAN", "MKT_SYMBOL": "CENTRALBK", "MKT": "NSE", "LOT": 1, "PRODUCT": "CASH", "REC_STATUS": "OPEN", "UPDATE_ACTION_1": "", "UPDATE_TIME_1": "", "UPDATE_ACTION_2": "", "UPDATE_TIME_2": "", "LOW_REC_PRICE": 65.0, "HIGH_REC_PRICE": 66.0, "TARGET": 70.0, "STOP_LOSS": 63.0, "PART_PROFIT_PRICE": "0", "FINAL_PROFIT_PRICE": "0", "EXIT_PRICE": "0", "ACK": "ACK"}, "22": {"STOCK": "MOIL LIMITED", "SOURCE": "BREEZE-iCLICK", "STRATEGY": "MARGIN", "BUY_SELL": "BUY", "REC_DATE": "12-Jun-2024", "REC_TIME": "10:29", "EXP_DATE": "12-Jun-2024", "SECURITY_ID": "4.1!20830", "ICICI_SYMBOL": "MOILIM", "MKT_SYMBOL": "MOIL", "MKT": "NSE", "LOT": 1, "PRODUCT": "CASH", "REC_STATUS": "CLOSE", "UPDATE_ACTION_1": " Book Full Profit:2024-06-12 10:41:28    ", "UPDATE_TIME_1": "10:41:28", "UPDATE_ACTION_2": "", "UPDATE_TIME_2": "", "LOW_REC_PRICE": 537.0, "HIGH_REC_PRICE": 537.0, "TARGET": 544.0, "STOP_LOSS": 508.0, "PART_PROFIT_PRICE": "0", "FINAL_PROFIT_PRICE": "541", "EXIT_PRICE": "0", "ACK": "ACK"}, "23": {"STOCK": "CONTAINER CORPORATION OF INDIA", "SOURCE": "BREEZE-iCLICK", "STRATEGY": "MARGIN", "BUY_SELL": "BUY", "REC_DATE": "12-Jun-2024", "REC_TIME": "10:31", "EXP_DATE": "12-Jun-2024", "SECURITY_ID": "4.1!4749", "ICICI_SYMBOL": "CONCOR", "MKT_SYMBOL": "CONCOR", "MKT": "NSE", "LOT": 1, "PRODUCT": "CASH", "REC_STATUS": "CLOSE", "UPDATE_ACTION_1": "   TGT1:2024-06-12 11:27:59  ", "UPDATE_TIME_1": "11:27:59", "UPDATE_ACTION_2": "", "UPDATE_TIME_2": "", "LOW_REC_PRICE": 1128.0, "HIGH_REC_PRICE": 1130.0, "TARGET": 1146.0, "STOP_LOSS": 1063.0, "PART_PROFIT_PRICE": "0", "FINAL_PROFIT_PRICE": "0", "EXIT_PRICE": "0", "ACK": "ACK"}, "24": {"STOCK": "ENGINEERS INDIA LTD", "SOURCE": "BREEZE-iCLICK", "STRATEGY": "MARGIN", "BUY_SELL": "BUY", "REC_DATE": "12-Jun-2024", "REC_TIME": "10:35", "EXP_DATE": "12-Jun-2024", "SECURITY_ID": "4.1!4907", "ICICI_SYMBOL": "ENGIND", "MKT_SYMBOL": "ENGINERSIN", "MKT": "NSE", "LOT": 1, "PRODUCT": "CASH", "REC_STATUS": "CLOSE", "UPDATE_ACTION_1": " Book Full Profit:2024-06-12 10:59:26    ", "UPDATE_TIME_1": "10:59:26", "UPDATE_ACTION_2": "", "UPDATE_TIME_2": "", "LOW_REC_PRICE": 252.0, "HIGH_REC_PRICE": 253.0, "TARGET": 256.0, "STOP_LOSS": 238.0, "PART_PROFIT_PRICE": "0", "FINAL_PROFIT_PRICE": "255", "EXIT_PRICE": "0", "ACK": "ACK"}, "25": {"STOCK": "RELIANCE INDUSTRIES", "SOURCE": "BREEZE-iCLICK", "STRATEGY": "MARGIN", "BUY_SELL": "BUY", "REC_DATE": "12-Jun-2024", "REC_TIME": "09:30", "EXP_DATE": "12-Jun-2024", "SECURITY_ID": "4.1!2885", "ICICI_SYMBOL": "RELIND", "MKT_SYMBOL": "RELIANCE", "MKT": "NSE", "LOT": 1, "PRODUCT": "CASH", "REC_STATUS": "CLOSE", "UPDATE_ACTION_1": " Book Full Profit:2024-06-12 10:38:06    ", "UPDATE_TIME_1": "10:38:06", "UPDATE_ACTION_2": "", "UPDATE_TIME_2": "", "LOW_REC_PRICE": 2927.0, "HIGH_REC_PRICE": 2930.0, "TARGET": 2956.0, "STOP_LOSS": 2765.0, "PART_PROFIT_PRICE": "0", "FINAL_PROFIT_PRICE": "2943", "EXIT_PRICE": "0", "ACK": "ACK"}, "26": {"STOCK": "STATE BANK OF INDIA", "SOURCE": "BREEZE-iCLICK", "STRATEGY": "GLADIATOR STOCKS", "BUY_SELL": "BUY", "REC_DATE": "12-Jun-2024", "REC_TIME": "10:55", "EXP_DATE": "12-Sep-2024", "SECURITY_ID": "4.1!3045", "ICICI_SYMBOL": "STABAN", "MKT_SYMBOL": "SBIN", "MKT": "NSE", "LOT": 1, "PRODUCT": "CASH", "REC_STATUS": "OPEN", "UPDATE_ACTION_1": "", "UPDATE_TIME_1": "", "UPDATE_ACTION_2": "", "UPDATE_TIME_2": "", "LOW_REC_PRICE": 825.0, "HIGH_REC_PRICE": 845.0, "TARGET": 945.0, "STOP_LOSS": 788.0, "PART_PROFIT_PRICE": "0", "FINAL_PROFIT_PRICE": "0", "EXIT_PRICE": "0", "ACK": "ACK"}, "27": {"STOCK": "L&T FINANCE LIMITED", "SOURCE": "BREEZE-iCLICK", "STRATEGY": "MARGIN", "BUY_SELL": "BUY", "REC_DATE": "12-Jun-2024", "REC_TIME": "12:23", "EXP_DATE": "12-Jun-2024", "SECURITY_ID": "4.1!24948", "ICICI_SYMBOL": "LTFINA", "MKT_SYMBOL": "LTF", "MKT": "NSE", "LOT": 1, "PRODUCT": "CASH", "REC_STATUS": "CLOSE", "UPDATE_ACTION_1": "   TGT1:2024-06-12 12:39:23  ", "UPDATE_TIME_1": "12:39:23", "UPDATE_ACTION_2": "", "UPDATE_TIME_2": "", "LOW_REC_PRICE": 169.0, "HIGH_REC_PRICE": 169.0, "TARGET": 171.0, "STOP_LOSS": 160.0, "PART_PROFIT_PRICE": "0", "FINAL_PROFIT_PRICE": "0", "EXIT_PRICE": "0", "ACK": "ACK"}, "28": {"STOCK": "BANK OF BARODA", "SOURCE": "BREEZE-iCLICK", "STRATEGY": "MARGIN", "BUY_SELL": "BUY", "REC_DATE": "12-Jun-2024", "REC_TIME": "14:06", "EXP_DATE": "12-Jun-2024", "SECURITY_ID": "4.1!4668", "ICICI_SYMBOL": "BANBAR", "MKT_SYMBOL": "BANKBARODA", "MKT": "NSE", "LOT": 1, "PRODUCT": "CASH", "REC_STATUS": "CLOSE", "UPDATE_ACTION_1": "Exit:2024-06-12 15:13:41     ", "UPDATE_TIME_1": "15:13:41", "UPDATE_ACTION_2": "LOSS", "UPDATE_TIME_2": "", "LOW_REC_PRICE": 283.0, "HIGH_REC_PRICE": 284.0, "TARGET": 287.0, "STOP_LOSS": 268.0, "PART_PROFIT_PRICE": "0", "FINAL_PROFIT_PRICE": "0", "EXIT_PRICE": "284", "ACK": "ACK"}, "29": {"STOCK": "COAL INDIA LIMITED", "SOURCE": "BREEZE-iCLICK", "STRATEGY": "MARGIN", "BUY_SELL": "BUY", "REC_DATE": "12-Jun-2024", "REC_TIME": "11:56", "EXP_DATE": "12-Jun-2024", "SECURITY_ID": "4.1!20374", "ICICI_SYMBOL": "COALIN", "MKT_SYMBOL": "COALINDIA", "MKT": "NSE", "LOT": 1, "PRODUCT": "CASH", "REC_STATUS": "CLOSE", "UPDATE_ACTION_1": "     SLTP:2024-06-12 14:14:05", "UPDATE_TIME_1": "14:14:05", "UPDATE_ACTION_2": "LOSS", "UPDATE_TIME_2": "", "LOW_REC_PRICE": 493.0, "HIGH_REC_PRICE": 493.0, "TARGET": 497.0, "STOP_LOSS": 466.0, "PART_PROFIT_PRICE": "0", "FINAL_PROFIT_PRICE": "0", "EXIT_PRICE": "0", "ACK": "ACK"}, "30": {"STOCK": "JIO FINANCIAL SERVICES LIMITED", "SOURCE": "BREEZE-iCLICK", "STRATEGY": "MARGIN", "BUY_SELL": "BUY", "REC_DATE": "12-Jun-2024", "REC_TIME": "14:46", "EXP_DATE": "12-Jun-2024", "SECURITY_ID": "4.1!18143", "ICICI_SYMBOL": "JIOFIN", "MKT_SYMBOL": "JIOFIN", "MKT": "NSE", "LOT": 1, "PRODUCT": "CASH", "REC_STATUS": "CLOSE", "UPDATE_ACTION_1": "   TGT1:2024-06-12 15:26:45  ", "UPDATE_TIME_1": "15:26:45", "UPDATE_ACTION_2": "", "UPDATE_TIME_2": "", "LOW_REC_PRICE": 356.0, "HIGH_REC_PRICE": 357.0, "TARGET": 362.0, "STOP_LOSS": 336.0, "PART_PROFIT_PRICE": "0", "FINAL_PROFIT_PRICE": "0", "EXIT_PRICE": "0", "ACK": "ACK"}}}